xc3_model_py-0.15.0.dist-info/METADATA
xc3_model_py-0.15.0.dist-info/WHEEL
xc3_model_py/__init__.py
xc3_model_py/__init__.pyi
xc3_model_py/animation.pyi
xc3_model_py/collision.pyi
xc3_model_py/material.pyi
xc3_model_py/monolib.pyi
xc3_model_py/shader_database.pyi
xc3_model_py/skinning.pyi
xc3_model_py/vertex.pyi
xc3_model_py/xc3_model_py.cpython-39-darwin.so
xc3_model_py-0.15.0.dist-info/RECORD
