Metadata-Version: 2.4
Name: xc3_model_py
Version: 0.15.0
Author: ScanMountGoat
